gif_mcp/__init__.py
gif_mcp/__main__.py
gif_mcp/server.py
gif_mcp-0.1.0.dist-info/METADATA
gif_mcp-0.1.0.dist-info/WHEEL
gif_mcp-0.1.0.dist-info/entry_points.txt
gif_mcp-0.1.0.dist-info/RECORD
