Metadata-Version: 2.4
Name: gif-mcp
Version: 0.1.0
Summary: 面向 GIF 元数据查询与逐帧导出的 MCP 服务器
Author-email: Your Name <your.email@example.com>
License: MIT
Keywords: animation,gif,image-processing,mcp
Classifier: Development Status :: 3 - Alpha
Classifier: Intended Audience :: Developers
Classifier: License :: OSI Approved :: MIT License
Classifier: Programming Language :: Python :: 3
Classifier: Programming Language :: Python :: 3.10
Classifier: Programming Language :: Python :: 3.11
Classifier: Programming Language :: Python :: 3.12
Requires-Python: >=3.10
Requires-Dist: mcp>=1.0.0
Requires-Dist: pillow>=10.0.0
Provides-Extra: dev
Requires-Dist: pytest>=7.0.0; extra == 'dev'
